kfsmedia/kfsmedia.py
kfsmedia-3.0.1.dist-info/METADATA
kfsmedia-3.0.1.dist-info/WHEEL
kfsmedia-3.0.1.dist-info/RECORD
