Metadata-Version: 2.1
Name: kfsmedia
Version: 3.0.1
Summary: 
Home-page: https://github.com/9-FS/kfsmedia
License: MIT
Author: 9FS
Author-email: pray4spam@googlemail.com
Requires-Python: >=3.12.0,<4.0.0
Classifier: License :: OSI Approved :: MIT License
Classifier: Programming Language :: Python :: 3
Classifier: Programming Language :: Python :: 3.12
Requires-Dist: kfsfstr (>=2.0.0,<3.0.0)
Requires-Dist: kfslog (>=3.0.0,<4.0.0)
Requires-Dist: olefile (>=0.47,<0.48)
Requires-Dist: pebble (>=5.0.0,<6.0.0)
Requires-Dist: pillow (>=10.2.0,<11.0.0)
Requires-Dist: requests (>=2.31.0,<3.0.0)
Project-URL: Repository, https://github.com/9-FS/kfsmedia
